odoo/addons/sale_expense_link/LICENSE
odoo/addons/sale_expense_link/README.rst
odoo/addons/sale_expense_link/__init__.py
odoo/addons/sale_expense_link/__manifest__.py
odoo/addons/sale_expense_link/i18n/de.po
odoo/addons/sale_expense_link/images/screen.png
odoo/addons/sale_expense_link/models/__init__.py
odoo/addons/sale_expense_link/models/hr_expense.py
odoo/addons/sale_expense_link/static/description/icon.png
odoo/addons/sale_expense_link/static/description/index.html
odoo/addons/sale_expense_link/tests/TEST_INSTRUCTIONS.rst
odoo/addons/sale_expense_link/views/hr_expense_sheet.xml
odoo_addon_sale_expense_link-16.0.1.0.0.dist-info/METADATA
odoo_addon_sale_expense_link-16.0.1.0.0.dist-info/WHEEL
odoo_addon_sale_expense_link-16.0.1.0.0.dist-info/top_level.txt
odoo_addon_sale_expense_link-16.0.1.0.0.dist-info/RECORD
